kvf/__init__.py
kvf/__main__.py
kvf-0.0.2.dist-info/LICENSE
kvf-0.0.2.dist-info/METADATA
kvf-0.0.2.dist-info/WHEEL
kvf-0.0.2.dist-info/entry_points.txt
kvf-0.0.2.dist-info/top_level.txt
kvf-0.0.2.dist-info/RECORD
