Metadata-Version: 2.1
Name: kvf
Version: 0.0.2
Summary: The key-value file format with sections
Home-page: https://github.com/pyrustic/kvf
Author: Pyrustic Architect
Author-email: rusticalex@yahoo.com
Maintainer: Pyrustic Architect
Maintainer-email: rusticalex@yahoo.com
License: MIT
Keywords: pyrustic
Classifier: Programming Language :: Python
Classifier: Programming Language :: Python :: 3
Classifier: License :: OSI Approved :: MIT License
Classifier: Operating System :: OS Independent
Classifier: Intended Audience :: Developers
Classifier: Development Status :: 4 - Beta
Requires-Python: >=3.5
License-File: LICENSE
Requires-Dist: paradict
Requires-Dist: braq
